chat_rag/__init__.py
chat_rag/data/__init__.py
chat_rag/data/models.py
chat_rag/data/parsers.py
chat_rag/data/splitters.py
chat_rag/embedding_models/__init__.py
chat_rag/embedding_models/base_model.py
chat_rag/embedding_models/e5_model.py
chat_rag/exceptions.py
chat_rag/intent_detection/__init__.py
chat_rag/intent_detection/clusterize_text.py
chat_rag/intent_detection/gen_intent.py
chat_rag/llms/__init__.py
chat_rag/llms/base_llm.py
chat_rag/llms/claude_client.py
chat_rag/llms/format_tools.py
chat_rag/llms/gemini_client.py
chat_rag/llms/hf_llm.py
chat_rag/llms/mistral_client.py
chat_rag/llms/openai_client.py
chat_rag/llms/together_client.py
chat_rag/llms/types.py
chat_rag/llms/vllm_client.py
chat_rag/rag.py
chat_rag/retrievers/__init__.py
chat_rag/retrievers/bm25_retriever.py
chat_rag/retrievers/colbert_retriever.py
chat_rag/retrievers/rerank_retriever.py
chat_rag/retrievers/retriever_client.py
chat_rag/retrievers/semantic_retriever.py
chat_rag/utils/__init__.py
chat_rag/utils/check_answ_questions.py
chat_rag/utils/gen_question.py
chat_rag/utils/reference_checker.py
chat_rag/utils/reranker.py
chat_rag-0.2.14.dist-info/METADATA
chat_rag-0.2.14.dist-info/WHEEL
chat_rag-0.2.14.dist-info/RECORD
