Metadata-Version: 2.3
Name: chat-rag
Version: 0.2.14
Summary: 
Author: Diego Peláez Paquico
Author-email: diego.pelaez@with-madrid.com
Requires-Python: >=3.13,<3.14
Classifier: Programming Language :: Python :: 3
Classifier: Programming Language :: Python :: 3.13
Provides-Extra: full
Requires-Dist: accelerate (>=0.31.0,<0.32.0) ; extra == "full"
Requires-Dist: aiohttp (>=3.12.15,<4.0.0)
Requires-Dist: anthropic (>=0.68.0,<0.69.0)
Requires-Dist: bm25s (>=0.1.7,<0.2.0) ; extra == "full"
Requires-Dist: certifi (>=2025.8.3,<2026.0.0)
Requires-Dist: cryptography (>=42.0.0)
Requires-Dist: docstring-parser (>=0.16,<0.17)
Requires-Dist: einops (>=0.6.1,<0.7.0) ; extra == "full"
Requires-Dist: google-genai (>=1.38.0,<2.0.0)
Requires-Dist: hdbscan (>=0.8.36,<0.9.0) ; extra == "full"
Requires-Dist: mistralai (>=1.8.2,<2.0.0)
Requires-Dist: numpy (>=2.3.3,<3.0.0)
Requires-Dist: openai (>=1.108.0,<2.0.0)
Requires-Dist: pandas (>=2.3.2,<3.0.0)
Requires-Dist: pillow (>=11.1.0,<12.0.0) ; extra == "full"
Requires-Dist: protobuf (>=4.25.8) ; extra == "full"
Requires-Dist: pyarrow (>=21.0.0,<22.0.0)
Requires-Dist: python-dotenv (>=0.21.0,<0.22.0)
Requires-Dist: ragatouille (>=0.0.9.post2,<0.0.10) ; extra == "full"
Requires-Dist: sentence-transformers (>=2.3.0,<3.0.0) ; extra == "full"
Requires-Dist: together (>=1.5.13,<2.0.0)
Requires-Dist: torch (==2.8.0) ; extra == "full"
Requires-Dist: tqdm (>=4.67.1,<5.0.0)
Requires-Dist: transformers (>=4.56.1,<5.0.0) ; extra == "full"
Requires-Dist: umap-learn (>=0.5.6,<0.6.0) ; extra == "full"
Requires-Dist: unstructured-inference (==0.7.21) ; extra == "full"
Requires-Dist: unstructured[pdf] (==0.12.0) ; (python_version >= "3.10" and python_version < "3.12") and (extra == "full")
Requires-Dist: urllib3 (>=2.5.0,<3.0.0)
